tiflash/__init__.py
tiflash/version.py
tiflash/core/__init__.py
tiflash/core/__main__.py
tiflash/core/api.py
tiflash/core/args.py
tiflash/core/core.py
tiflash/js/args.js
tiflash/js/ccxml.js
tiflash/js/erase.js
tiflash/js/expression.js
tiflash/js/flash.js
tiflash/js/list.js
tiflash/js/main.js
tiflash/js/memory.js
tiflash/js/operation.js
tiflash/js/options.js
tiflash/js/register.js
tiflash/js/reset.js
tiflash/js/result.js
tiflash/js/session.js
tiflash/js/verify.js
tiflash/utils/__init__.py
tiflash/utils/ccs.py
tiflash/utils/ccxml.py
tiflash/utils/config.py
tiflash/utils/connections.py
tiflash/utils/cpus.py
tiflash/utils/debug_probes.json
tiflash/utils/detect.py
tiflash/utils/devices.py
tiflash/utils/dss.py
tiflash/utils/flash_properties.py
tiflash/utils/result.py
tiflash/utils/xds110.py
tiflash/utils/xmlhelper.py
tiflash-1.3.0.dist-info/DESCRIPTION.rst
tiflash-1.3.0.dist-info/METADATA
tiflash-1.3.0.dist-info/RECORD
tiflash-1.3.0.dist-info/WHEEL
tiflash-1.3.0.dist-info/entry_points.txt
tiflash-1.3.0.dist-info/metadata.json
tiflash-1.3.0.dist-info/top_level.txt
