Metadata-Version: 2.0
Name: tiflash
Version: 1.3.0
Summary: Unofficial python module for flashing TI devices.
Home-page: https://tiflash.readthedocs.io
Author: Cameron Webb
Author-email: webbjcam@gmail.com
License: MIT
Download-URL: https://github.com/webbcam/tiflash/tarball/1.3.0
Project-URL: Source, https://github.com/webbcam/tiflash
Project-URL: Documentation, https://tiflash.readthedocs.io
Platform: UNKNOWN
Classifier: Development Status :: 5 - Production/Stable
Classifier: License :: OSI Approved :: MIT License
Classifier: Operating System :: OS Independent
Classifier: Programming Language :: Python :: 2.7
Classifier: Programming Language :: Python :: 3.6
Classifier: Programming Language :: Python :: 3.7
Classifier: Topic :: Software Development :: Embedded Systems
Classifier: Topic :: Software Development :: Libraries :: Python Modules
Classifier: Topic :: Software Development :: Testing
Classifier: Intended Audience :: Developers
Requires-Python: >=2.7.13, <4
Requires-Dist: pyserial (>=3.4); platform_system != "Windows"
